LICENSE
MANIFEST.in
README
setup.py
cpmerge/__init__.py
cpmerge/cpmerge.py
cpmerge/icon.png
cpmerge.egg-info/PKG-INFO
cpmerge.egg-info/SOURCES.txt
cpmerge.egg-info/dependency_links.txt
cpmerge.egg-info/entry_points.txt
cpmerge.egg-info/requires.txt
cpmerge.egg-info/top_level.txt