Metadata-Version: 1.1
Name: cpmerge
Version: 1.0.5
Summary: A simple clipboard manager to synchronize the CLIPBOARD and PRIMARY selection under linux
Home-page: http://jonaspfannschmidt.com/cpmerge
Author: Jonas Pfannschmidt
Author-email: jonas.pfannschmidt@gmail.com
License: MIT
Platform: UNKNOWN
Classifier: Programming Language :: Python :: 2.7
Classifier: Intended Audience :: End Users/Desktop
Classifier: License :: OSI Approved :: MIT License
Classifier: Operating System :: POSIX :: Linux
Classifier: Topic :: Utilities
Classifier: Environment :: X11 Applications
